navigator_sdk/__init__.py
navigator_sdk/client.py
navigator_sdk/config.py
navigator_sdk/handler.py
navigator_sdk/py.typed
navigator_sdk/retry.py
navigator_sdk/setup.py
navigator_sdk-0.4.2.dist-info/WHEEL
navigator_sdk-0.4.2.dist-info/METADATA
navigator_sdk-0.4.2.dist-info/RECORD
