Metadata-Version: 2.3
Name: navigator-sdk
Version: 0.4.2
Summary: A simple and fast way to share logs with Navigator
Author: Dhrumil Patel
Author-email: Dhrumil Patel <dhrumilcse14@gmail.com>
Requires-Dist: httpx>=0.27.0
Requires-Dist: python-dotenv>=1.2.1
Requires-Dist: ruff>=0.14.6
Requires-Python: >=3.10
